{
    "fluentMethods": true,
    "relationships": [
        {
            "relationshipType": "one-to-many",
            "relationshipName": "countryStates",
            "otherEntityName": "state",
            "otherEntityRelationshipName": "country"
        }
    ],
    "fields": [
        {
            "fieldName": "name",
            "fieldType": "String"
        }
    ],
    "changelogDate": "20180205123527",
    "entityTableName": "country",
    "dto": "no",
    "pagination": "no",
    "service": "no",
    "jpaMetamodelFiltering": false,
    "skipServer": true,
    "microserviceName": "SupplierRegisteration"
}